LICENSE
README.md
setup.cfg
setup.py
crystalpayio/__init__.py
crystalpayio/crystalpayio.py
crystalpayio/webhook_manager.py
crystalpayio.egg-info/PKG-INFO
crystalpayio.egg-info/SOURCES.txt
crystalpayio.egg-info/dependency_links.txt
crystalpayio.egg-info/top_level.txt
crystalpayio/api/__init__.py
crystalpayio/api/get_asyncio_api.py
crystalpayio/utils/__init__.py
crystalpayio/utils/base.py
crystalpayio/utils/exceptions.py
crystalpayio/utils/models.py