Metadata-Version: 2.1
Name: crystalpayio
Version: 1.0.5
Summary: Asynchronous wrapper for CrystalPay API
Home-page: https://github.com/Fsoky/aiocrystalpay
Author: Fsoky
Author-email: cyberuest0x12@gmail.com
License: UNKNOWN
Keywords: api crystalpay asyncio crypto
Platform: UNKNOWN
License-File: LICENSE
